Metadata-Version: 1.0
Name: yandex-object-storage
Version: 0.0.1
Summary: Yandex object storage
Home-page: UNKNOWN
Author: Alex Demure
Author-email: alexanderdemure@gmail.com
License: MIT
Keywords: yandex
Platform: UNKNOWN
